whatsapp/__init__.py
whatsapp/whatsapp.py
whatsapp_api-0.0.3.dist-info/METADATA
whatsapp_api-0.0.3.dist-info/WHEEL
whatsapp_api-0.0.3.dist-info/top_level.txt
whatsapp_api-0.0.3.dist-info/RECORD
