Metadata-Version: 2.1
Name: whatsapp-api
Version: 0.0.3
Summary: The unofficial python api for whatsapp
Home-page: UNKNOWN
Author: Ayush Goyal
Author-email: ayushgoyal.iitkgp@gmail.com
License: UNKNOWN
Keywords: whatsapp,python
Platform: UNKNOWN
Classifier: Development Status :: 3 - Alpha
Classifier: Intended Audience :: Education
Classifier: Programming Language :: Python :: 2
Classifier: Programming Language :: Python :: 3
Classifier: Operating System :: MacOS :: MacOS X
Classifier: Operating System :: Microsoft :: Windows
Requires-Dist: requests
Requires-Dist: defcon-utils
